freqtrade_api_client/__init__.py
freqtrade_api_client/api/__init__.py
freqtrade_api_client/api/auth/__init__.py
freqtrade_api_client/api/auth/token_login_api_v1_token_login_post.py
freqtrade_api_client/api/auth/token_refresh_api_v1_token_refresh_post.py
freqtrade_api_client/api/botcontrol/__init__.py
freqtrade_api_client/api/botcontrol/reload_config_api_v1_reload_config_post.py
freqtrade_api_client/api/botcontrol/start_api_v1_start_post.py
freqtrade_api_client/api/botcontrol/stop_api_v1_stop_post.py
freqtrade_api_client/api/botcontrol/stop_buy_api_v1_stopbuy_post.py
freqtrade_api_client/api/candle_data/__init__.py
freqtrade_api_client/api/candle_data/list_available_pairs_api_v1_available_pairs_get.py
freqtrade_api_client/api/candle_data/pair_candles_api_v1_pair_candles_get.py
freqtrade_api_client/api/candle_data/pair_history_api_v1_pair_history_get.py
freqtrade_api_client/api/candle_data/plot_config_api_v1_plot_config_get.py
freqtrade_api_client/api/default/__init__.py
freqtrade_api_client/api/default/ping_api_v1_ping_get.py
freqtrade_api_client/api/info/__init__.py
freqtrade_api_client/api/info/balance_api_v1_balance_get.py
freqtrade_api_client/api/info/blacklist_api_v1_blacklist_get.py
freqtrade_api_client/api/info/blacklist_delete_api_v1_blacklist_delete.py
freqtrade_api_client/api/info/blacklist_post_api_v1_blacklist_post.py
freqtrade_api_client/api/info/count_api_v1_count_get.py
freqtrade_api_client/api/info/daily_api_v1_daily_get.py
freqtrade_api_client/api/info/delete_lock_api_v1_locks_lockid_delete.py
freqtrade_api_client/api/info/delete_lock_pair_api_v1_locks_delete_post.py
freqtrade_api_client/api/info/edge_api_v1_edge_get.py
freqtrade_api_client/api/info/health_api_v1_health_get.py
freqtrade_api_client/api/info/locks_api_v1_locks_get.py
freqtrade_api_client/api/info/logs_api_v1_logs_get.py
freqtrade_api_client/api/info/performance_api_v1_performance_get.py
freqtrade_api_client/api/info/profit_api_v1_profit_get.py
freqtrade_api_client-0.1.0.dist-info/WHEEL
freqtrade_api_client-0.1.0.dist-info/METADATA
freqtrade_api_client-0.1.0.dist-info/RECORD
